optimistic_pessimistic_evaluator/__init__.py
optimistic_pessimistic_evaluator/main.py
optimistic_pessimistic_evaluator/prompts.py
optimistic_pessimistic_evaluator-2025.12.21151045.dist-info/METADATA
optimistic_pessimistic_evaluator-2025.12.21151045.dist-info/WHEEL
optimistic_pessimistic_evaluator-2025.12.21151045.dist-info/top_level.txt
optimistic_pessimistic_evaluator-2025.12.21151045.dist-info/RECORD
