Metadata-Version: 2.4
Name: optimistic-pessimistic-evaluator
Version: 2025.12.21151045
Summary: A new package is designed to facilitate structured evaluation of a system's performance comparison between optimistic and pessimistic approaches. It takes a textual description or data snippet as inpu
Author-email: optimistic-pessimistic-evaluator <hi@eugene.plus>
License: MIT
Project-URL: Homepage, https://github.com/chigwell/optimistic-pessimistic-evaluator
Requires-Python: >=3.9
Requires-Dist: langchain-llm7>=0.0.0
Requires-Dist: llmatch-messages>=0.0.0
Requires-Dist: langchain-core>=0.3.0
